avrae_ls/__init__.py
avrae_ls/__main__.py
avrae_ls/alias_preview.py
avrae_ls/alias_tests.py
avrae_ls/api.py
avrae_ls/argparser.py
avrae_ls/argument_parsing.py
avrae_ls/ast_utils.py
avrae_ls/code_actions.py
avrae_ls/codes.py
avrae_ls/completions.py
avrae_ls/config.py
avrae_ls/context.py
avrae_ls/cvars.py
avrae_ls/diagnostics.py
avrae_ls/dice.py
avrae_ls/lsp_utils.py
avrae_ls/parser.py
avrae_ls/runtime.py
avrae_ls/server.py
avrae_ls/signature_help.py
avrae_ls/source_context.py
avrae_ls/symbols.py
avrae_ls/type_inference.py
avrae_ls/type_system.py
draconic/LICENSE
draconic/__init__.py
draconic/exceptions.py
draconic/helpers.py
draconic/interpreter.py
draconic/string.py
draconic/types.py
draconic/utils.py
draconic/versions.py
avrae_ls-0.7.1.dist-info/METADATA
avrae_ls-0.7.1.dist-info/WHEEL
avrae_ls-0.7.1.dist-info/entry_points.txt
avrae_ls-0.7.1.dist-info/licenses/LICENSE
avrae_ls-0.7.1.dist-info/RECORD
