Metadata-Version: 2.4
Name: avrae-ls
Version: 0.7.1
Summary: Language server for Avrae draconic aliases
Author: 1drturtle
License: MIT License
License-File: LICENSE
Requires-Python: >=3.11
Requires-Dist: d20>=1.1.2
Requires-Dist: httpx>=0.27
Requires-Dist: lsprotocol>=2023.0.1
Requires-Dist: pygls>=1.3.1
Requires-Dist: pyyaml>=6.0
Provides-Extra: dev
Requires-Dist: pytest-asyncio>=0.23; extra == 'dev'
Requires-Dist: pytest-cov>=7.0.0; extra == 'dev'
Requires-Dist: pytest>=8.3; extra == 'dev'
Requires-Dist: ruff>=0.6; extra == 'dev'
